py2pip/__init__.py
py2pip/__main__.py
py2pip/config.py
py2pip/parser.py
py2pip/process.py
py2pip/simulator.py
py2pip/utils.py
py2pip-1.0.2.dist-info/METADATA
py2pip-1.0.2.dist-info/WHEEL
py2pip-1.0.2.dist-info/entry_points.txt
py2pip-1.0.2.dist-info/top_level.txt
py2pip-1.0.2.dist-info/RECORD
