Metadata-Version: 2.1
Name: py2pip
Version: 1.0.2
Summary: Master package for Py2PIP
Home-page: http://pypi.python.org/pypi/py2pip
Author: Manish Kumar
Author-email: kumarmanish890@gmail.com
License: MIT
Keywords: Developer,Python,Version,Compatibility
Platform: UNKNOWN
Classifier: Development Status :: 5 - Production/Stable
Classifier: Environment :: No Input/Output (Daemon)
Classifier: Framework :: AsyncIO
Classifier: Programming Language :: Python
Classifier: Programming Language :: Python :: 3
Classifier: Programming Language :: Python :: 3.7
Classifier: Programming Language :: Python :: 3.6
Classifier: Programming Language :: Python :: 3 :: Only
Classifier: License :: OSI Approved :: MIT License
Classifier: Operating System :: POSIX :: Linux
Classifier: Topic :: Internet :: WWW/HTTP
Classifier: Topic :: Internet :: WWW/HTTP :: Dynamic Content
Classifier: Topic :: Internet :: WWW/HTTP :: Session
Classifier: Topic :: Text Processing :: Markup :: HTML
Classifier: Natural Language :: English
Classifier: Intended Audience :: Developers
Requires-Python: >=3
Requires-Dist: setuptools
Requires-Dist: packaging
Requires-Dist: beautifulsoup4
Requires-Dist: aiohttp
